{
  "mode": "pre",
  "tag": "beta",
  "initialVersions": {
    "@clerk/backend": "0.31.3",
    "@clerk/chrome-extension": "0.4.10",
    "@clerk/clerk-js": "4.63.0",
    "eslint-config-custom": "0.3.0",
    "@clerk/clerk-expo": "0.19.12",
    "@clerk/fastify": "0.6.17",
    "gatsby-plugin-clerk": "4.4.18",
    "@clerk/localizations": "1.26.7",
    "@clerk/nextjs": "4.25.7",
    "@clerk/clerk-react": "4.27.0",
    "@clerk/remix": "3.1.0",
    "@clerk/clerk-sdk-node": "4.12.16",
    "@clerk/shared": "1.0.0",
    "@clerk/themes": "1.7.9",
    "@clerk/types": "3.57.0",
    "@clerk/elements": "0.1.3"
  },
  "changesets": [
    "afraid-experts-eat",
    "afraid-eyes-relate",
    "afraid-falcons-leave",
    "afraid-nails-play",
    "angry-beers-play",
    "angry-clocks-attend",
    "angry-cows-refuse",
    "beige-eyes-relate",
    "beige-stingrays-explode",
    "big-ads-provide",
    "blue-garlics-remain",
    "blue-ghosts-float",
    "blue-grapes-marry",
    "blue-horses-call",
    "blue-lies-drop",
    "brave-suits-drive",
    "bright-dragons-join",
    "bright-knives-jump",
    "bright-plants-swim",
    "bright-trainers-sort",
    "bright-ways-provide",
    "brown-candles-rule",
    "brown-clouds-divide",
    "brown-ducks-reply",
    "brown-foxes-own",
    "brown-lemons-film",
    "brown-mangos-jam",
    "brown-masks-wonder",
    "brown-pets-smile",
    "brown-trees-sniff",
    "calm-carrots-beg",
    "calm-forks-grow",
    "calm-humans-suffer",
    "calm-pears-attack",
    "calm-socks-cough",
    "calm-tips-grin",
    "chatty-beans-fix",
    "chatty-berries-jump",
    "chatty-boats-tease",
    "chatty-bottles-rhyme",
    "chatty-coins-flash",
    "chatty-months-smell",
    "chatty-years-hope",
    "chilled-bikes-rule",
    "chilled-boxes-kick",
    "chilly-donuts-work",
    "chilly-maps-jog",
    "chilly-pens-speak",
    "clever-bananas-turn",
    "clever-cups-knock",
    "clever-hounds-flow",
    "clever-moose-act",
    "clever-scissors-reflect",
    "clever-vans-flash",
    "clever-wasps-invite",
    "cold-coins-listen",
    "cold-comics-serve",
    "cold-jars-roll",
    "cold-points-carry",
    "cold-ravens-eat",
    "cool-cars-float",
    "cool-ties-grin",
    "cuddly-cougars-check",
    "cuddly-fireants-switch",
    "cuddly-houses-sniff",
    "cuddly-oranges-ring",
    "cuddly-tips-speak",
    "curly-baboons-argue",
    "curly-cycles-march",
    "curly-news-push",
    "curly-parrots-camp",
    "curly-toes-complain",
    "curvy-chefs-sneeze",
    "curvy-cows-destroy",
    "curvy-kids-sip",
    "curvy-mails-rhyme",
    "curvy-suns-roll",
    "curvy-timers-play",
    "cyan-dodos-provide",
    "cyan-insects-travel",
    "cyan-pumpkins-try",
    "cyan-rockets-fail",
    "cyan-stingrays-own",
    "dirty-chefs-sell",
    "dirty-icons-rescue",
    "dirty-mayflies-heal",
    "dirty-panthers-begin",
    "dirty-rockets-cheat",
    "dirty-sheep-warn",
    "dirty-swans-joke",
    "dry-beds-boil",
    "dry-feet-join",
    "dry-pens-listen",
    "dry-sheep-poke",
    "dry-students-reflect",
    "dull-ants-argue",
    "dull-moose-kiss",
    "dull-seals-type",
    "dull-stingrays-fix",
    "dull-wasps-begin",
    "early-candles-shop",
    "early-carpets-fly",
    "early-cars-cross",
    "early-dryers-lay",
    "early-forks-argue",
    "early-timers-wave",
    "early-tomatoes-hide",
    "eight-badgers-speak",
    "eight-cherries-tan",
    "eight-dolphins-float",
    "eight-geese-hang",
    "eight-plants-melt",
    "eight-pots-guess",
    "eighty-planets-provide",
    "eighty-walls-appear",
    "eleven-bananas-joke",
    "eleven-clouds-wave",
    "empty-jars-press",
    "empty-lions-pull",
    "empty-radios-sleep",
    "fair-bears-build",
    "fair-cameras-boil",
    "fair-donuts-approve",
    "fair-peas-promise",
    "famous-bugs-tell",
    "famous-carrots-notice",
    "famous-forks-buy",
    "famous-penguins-bow",
    "famous-spies-clean",
    "famous-waves-tie",
    "famous-years-tickle",
    "fast-ads-mix",
    "fast-games-hide",
    "fast-hornets-report",
    "fast-swans-smile",
    "few-beers-wink",
    "few-kids-design",
    "few-rings-push",
    "fifty-clocks-act",
    "fifty-rats-rhyme",
    "fifty-shirts-grin",
    "fifty-snakes-accept",
    "five-boxes-agree",
    "five-hotels-wash",
    "five-lamps-beam",
    "flat-ants-worry",
    "flat-bugs-visit",
    "flat-clocks-clap",
    "flat-donuts-sleep",
    "flat-lions-divide",
    "flat-pots-hear",
    "flat-waves-cheat",
    "fluffy-chicken-explain",
    "fluffy-olives-boil",
    "fluffy-olives-listen",
    "fluffy-pets-greet",
    "fluffy-queens-tap",
    "forty-frogs-invite",
    "forty-suits-care",
    "forty-trains-rest",
    "four-cats-poke",
    "four-crabs-sneeze",
    "four-guests-drive",
    "four-pandas-grab",
    "fresh-crews-lick",
    "fresh-kings-join",
    "friendly-apricots-camp",
    "friendly-boats-chew",
    "friendly-months-film",
    "friendly-parrots-nail",
    "friendly-swans-clap",
    "friendly-tables-chew",
    "friendly-vans-develop",
    "funny-apricots-buy",
    "funny-avocados-shout",
    "funny-gifts-cough",
    "funny-lamps-work",
    "funny-pianos-double",
    "funny-pots-brush",
    "fuzzy-horses-fix",
    "fuzzy-shoes-battle",
    "fuzzy-years-taste",
    "gentle-berries-teach",
    "gentle-donkeys-talk",
    "gentle-kiwis-argue",
    "gentle-pants-matter",
    "gentle-radios-shout",
    "gentle-toes-obey",
    "gentle-toys-melt",
    "giant-bags-lie",
    "giant-bags-stare",
    "giant-donuts-hear",
    "giant-rice-crash",
    "gold-beans-obey",
    "gold-crews-joke",
    "gold-fireants-sort",
    "gold-islands-cover",
    "gold-shrimps-behave",
    "good-buttons-drum",
    "good-dogs-attack",
    "gorgeous-apples-clap",
    "gorgeous-baboons-float",
    "gorgeous-camels-mate",
    "gorgeous-camels-whisper",
    "gorgeous-insects-reply",
    "gorgeous-stingrays-lay",
    "great-falcons-knock",
    "great-moons-suffer",
    "great-plums-buy",
    "green-rocks-chew",
    "green-spies-shave",
    "green-vans-sniff",
    "grumpy-drinks-turn",
    "grumpy-laws-play",
    "grumpy-rats-laugh",
    "grumpy-suns-boil",
    "happy-dolls-taste",
    "happy-panthers-approve",
    "happy-points-relax",
    "happy-trees-burn",
    "happy-worms-smell",
    "healthy-eyes-marry",
    "healthy-fans-move",
    "healthy-planets-clap",
    "healthy-walls-fold",
    "heavy-falcons-help",
    "heavy-horses-nail",
    "heavy-phones-rest",
    "hip-chefs-yell",
    "hip-eagles-clap",
    "hip-monkeys-boil",
    "hip-planets-reply",
    "honest-onions-wink",
    "honest-onions-work",
    "honest-pigs-smoke",
    "hot-ducks-wink",
    "hot-fireants-kiss",
    "hungry-bears-allow",
    "hungry-bikes-clean",
    "hungry-bottles-flow",
    "hungry-crabs-burn",
    "hungry-lies-burn",
    "hungry-news-bathe",
    "itchy-chairs-argue",
    "itchy-chairs-call",
    "itchy-papayas-dress",
    "khaki-buttons-march",
    "khaki-seahorses-compete",
    "khaki-spoons-teach",
    "khaki-timers-work",
    "kind-eagles-hope",
    "kind-onions-think",
    "large-needles-sparkle",
    "late-cooks-collect",
    "late-dolphins-peel",
    "late-flies-switch",
    "late-geckos-impress",
    "late-insects-doubt",
    "late-jobs-sort",
    "late-pillows-notice",
    "late-wasps-attack",
    "late-wolves-mate",
    "lazy-lizards-tap",
    "lazy-planes-run",
    "lazy-turtles-nail",
    "lemon-cameras-talk",
    "lemon-crews-do",
    "lemon-kings-love",
    "lemon-rockets-explode",
    "lemon-rocks-act",
    "lemon-starfishes-buy",
    "lemon-turkeys-provide",
    "lemon-worms-chew",
    "light-apples-joke",
    "light-buckets-check",
    "light-chairs-impress",
    "light-cherries-build",
    "light-doors-invent",
    "light-doors-teach",
    "light-shirts-lick",
    "light-snakes-type",
    "light-spoons-divide",
    "little-apes-notice",
    "little-dolphins-scream",
    "little-numbers-jam",
    "little-shoes-give",
    "long-beds-mate",
    "long-dancers-whisper",
    "long-icons-share",
    "long-starfishes-roll",
    "loud-countries-hang",
    "loud-lions-compete",
    "loud-panthers-poke",
    "loud-tomatoes-jam",
    "lovely-experts-deny",
    "lovely-jars-explode",
    "lovely-jobs-arrive",
    "lovely-mirrors-remember",
    "lovely-plums-sin",
    "lovely-spies-kiss",
    "lovely-students-occur",
    "lovely-teachers-hammer",
    "lucky-bees-whisper",
    "lucky-houses-exercise",
    "lucky-ligers-brush",
    "many-bottles-watch",
    "many-days-unite",
    "many-dragons-carry",
    "many-flowers-heal",
    "many-moons-matter",
    "many-onions-travel",
    "many-pillows-fold",
    "many-starfishes-warn",
    "many-weeks-march",
    "mean-frogs-hammer",
    "mean-houses-juggle",
    "mean-numbers-grin",
    "mean-poets-bow",
    "metal-baboons-vanish",
    "metal-cougars-fail",
    "metal-days-float",
    "metal-ears-cheat",
    "metal-kings-tease",
    "metal-moons-applaud",
    "metal-olives-press",
    "metal-toes-smell",
    "metal-wolves-wave",
    "mighty-bulldogs-try",
    "mighty-cooks-admire",
    "mighty-melons-greet",
    "mighty-pugs-knock",
    "mighty-queens-exist",
    "mighty-rice-marry",
    "mighty-ways-learn",
    "modern-buses-sort",
    "modern-mayflies-sort",
    "modern-oranges-swim",
    "modern-plums-invent",
    "modern-starfishes-rush",
    "moody-pears-trade",
    "moody-radios-begin",
    "moody-trainers-bow",
    "moody-zoos-deliver",
    "nasty-books-tap",
    "nasty-lemons-obey",
    "nasty-mirrors-arrive",
    "neat-crabs-know",
    "neat-lies-thank",
    "neat-mice-invite",
    "neat-numbers-decide",
    "neat-poets-push",
    "nervous-books-ring",
    "nervous-cups-push",
    "nervous-kings-deny",
    "nervous-wombats-sin",
    "new-cougars-taste",
    "new-dolphins-raise",
    "new-eels-mix",
    "new-points-train",
    "new-points-turn",
    "new-wasps-impress",
    "nice-dingos-argue",
    "nice-doors-fail",
    "nice-starfishes-itch",
    "nine-beans-travel",
    "nine-cooks-retire",
    "nine-mangos-look",
    "nine-mayflies-smoke",
    "nine-yaks-buy",
    "ninety-apricots-yell",
    "ninety-planets-lick",
    "odd-dogs-tan",
    "odd-eels-ring",
    "odd-islands-attack",
    "odd-lemons-reply",
    "odd-snakes-study",
    "odd-tigers-trade",
    "odd-toes-develop",
    "old-actors-beg",
    "old-ads-push",
    "old-guests-watch",
    "old-onions-swim",
    "old-scissors-leave",
    "old-timers-obey",
    "olive-bags-reflect",
    "olive-beers-scream",
    "olive-files-listen",
    "olive-kings-retire",
    "olive-steaks-end",
    "orange-bears-return",
    "orange-bees-double",
    "orange-bottles-raise",
    "orange-eyes-nail",
    "orange-files-end",
    "orange-hats-approve",
    "orange-melons-destroy",
    "orange-pumpkins-poke",
    "perfect-ants-joke",
    "perfect-hairs-vanish",
    "pink-baboons-allow",
    "pink-days-drum",
    "pink-eggs-enjoy",
    "pink-gifts-retire",
    "pink-swans-fetch",
    "polite-comics-cheer",
    "polite-kiwis-arrive",
    "poor-carpets-act",
    "poor-geese-rescue",
    "poor-horses-press",
    "poor-kings-marry",
    "poor-rats-pump",
    "popular-monkeys-clap",
    "popular-parents-hope",
    "popular-singers-sort",
    "pretty-mice-share",
    "pretty-months-greet",
    "pretty-owls-switch",
    "pretty-scissors-thank",
    "pretty-singers-change",
    "proud-carpets-visit",
    "proud-frogs-confess",
    "proud-hairs-check",
    "proud-trees-yell",
    "purple-ligers-wave",
    "purple-pumas-study",
    "purple-rules-prove",
    "quick-countries-notice",
    "quick-countries-scream",
    "quick-gorillas-grin",
    "quick-poems-sip",
    "quick-trains-rush",
    "quick-walls-share",
    "quiet-cougars-watch",
    "quiet-jokes-travel",
    "quiet-kings-relate",
    "quiet-toes-hide",
    "rare-bottles-sell",
    "rare-bulldogs-cheer",
    "rare-ladybugs-mate",
    "rare-poets-deliver",
    "rare-students-sell",
    "real-cougars-design",
    "real-lobsters-flash",
    "real-taxis-compare",
    "red-coats-itch",
    "red-monkeys-sing",
    "red-shrimps-hunt",
    "red-suns-perform",
    "red-worms-fetch",
    "rich-actors-cross",
    "rich-readers-obey",
    "rich-sloths-count",
    "rotten-cougars-refuse",
    "rotten-ligers-move",
    "rotten-rats-protect",
    "rotten-tigers-rescue",
    "rotten-ways-do",
    "rude-cows-fry",
    "rude-deers-fetch",
    "rude-falcons-grow",
    "rude-falcons-thank",
    "rude-gorillas-smash",
    "rude-jobs-yawn",
    "rude-lamps-yawn",
    "rude-needles-nail",
    "rude-plums-move",
    "selfish-coats-know",
    "selfish-eggs-sort",
    "selfish-flies-care",
    "selfish-peaches-glow",
    "selfish-planes-sing",
    "selfish-pugs-repair",
    "selfish-trains-breathe",
    "serious-doors-reflect",
    "serious-rivers-repeat",
    "seven-lizards-deliver",
    "seven-tables-tan",
    "shaggy-points-cheer",
    "shaggy-pumpkins-tap",
    "sharp-donuts-drum",
    "sharp-trains-ring",
    "sharp-zebras-warn",
    "shiny-games-buy",
    "shiny-glasses-switch",
    "shiny-pumas-share",
    "shiny-ties-complain",
    "short-cheetahs-punch",
    "short-eagles-search",
    "short-kings-mate",
    "shy-bikes-draw",
    "shy-eggs-smell",
    "silent-carpets-jam",
    "silent-comics-roll",
    "silent-dolphins-accept",
    "silly-bikes-lick",
    "silly-emus-boil",
    "silly-icons-kick",
    "silly-poems-tease",
    "silly-tips-cry",
    "silly-zebras-dream",
    "silver-cats-appear",
    "silver-weeks-roll",
    "six-doors-teach",
    "six-experts-itch",
    "six-kangaroos-serve",
    "six-lies-refuse",
    "six-walls-fry",
    "sixty-boats-stare",
    "sixty-dancers-lie",
    "sixty-frogs-pump",
    "sixty-islands-jump",
    "sixty-lions-obey",
    "sixty-months-listen",
    "sixty-pianos-look",
    "sixty-rats-bathe",
    "slimy-brooms-smoke",
    "slimy-lions-applaud",
    "slimy-singers-glow",
    "slimy-ties-approve",
    "slimy-windows-grab",
    "slimy-wolves-burn",
    "slow-bugs-exist",
    "slow-dancers-watch",
    "slow-eels-fly",
    "slow-wombats-battle",
    "small-cats-check",
    "small-cooks-boil",
    "small-dodos-marry",
    "small-ladybugs-mate",
    "small-months-sing",
    "small-swans-stare",
    "smart-queens-kiss",
    "smart-suns-train",
    "smart-ways-sing",
    "smooth-baboons-shake",
    "smooth-forks-flash",
    "smooth-numbers-shout",
    "smooth-pets-rhyme",
    "soft-apples-chew",
    "soft-birds-thank",
    "soft-donkeys-promise",
    "soft-fireants-jog",
    "soft-rats-grab",
    "soft-swans-swim",
    "soft-trees-battle",
    "sour-ads-wave",
    "sour-avocados-sin",
    "sour-comics-stare",
    "sour-frogs-type",
    "spicy-feet-buy",
    "spotty-apples-march",
    "spotty-boxes-do",
    "spotty-boxes-fold",
    "spotty-hotels-cheat",
    "spotty-nails-double",
    "spotty-penguins-admire",
    "spotty-ravens-sleep",
    "spotty-roses-push",
    "spotty-tomatoes-wonder",
    "stale-hats-jump",
    "stale-nails-deny",
    "strange-needles-learn",
    "strange-ravens-own",
    "strange-trains-bow",
    "strong-cows-sit",
    "strong-melons-sort",
    "stupid-suits-accept",
    "stupid-toys-remain",
    "sweet-chairs-fry",
    "sweet-ladybugs-sneeze",
    "sweet-planes-learn",
    "sweet-pumas-press",
    "sweet-queens-tan",
    "swift-rocks-nail",
    "tall-radios-sing",
    "tall-roses-invent",
    "tall-seahorses-cheat",
    "tame-beds-promise",
    "tame-forks-refuse",
    "tame-olives-check",
    "tame-rings-add",
    "tasty-beans-sell",
    "tasty-countries-walk",
    "tasty-months-try",
    "tasty-phones-lie",
    "tasty-terms-fly",
    "ten-crews-rhyme",
    "ten-dryers-share",
    "ten-dryers-sniff",
    "ten-mugs-film",
    "ten-nails-whisper",
    "ten-spies-brake",
    "ten-starfishes-study",
    "ten-taxis-lick",
    "tender-peaches-yell",
    "tender-pets-wash",
    "tender-phones-explain",
    "tender-wasps-hope",
    "thick-doors-smile",
    "thick-paws-beg",
    "thick-poems-play",
    "thin-coats-serve",
    "thin-fireants-fix",
    "thin-phones-drop",
    "thin-trees-poke",
    "thirty-chicken-divide",
    "thirty-cooks-cheer",
    "thirty-doors-peel",
    "thirty-insects-exist",
    "thirty-kings-trade",
    "thirty-news-mate",
    "thirty-taxis-ring",
    "three-planes-tell",
    "tidy-buttons-pump",
    "tidy-dots-lick",
    "tidy-guests-dance",
    "tidy-shrimps-study",
    "tiny-beds-yell",
    "tiny-crabs-eat",
    "tiny-forks-sit",
    "tiny-pants-change",
    "tiny-ravens-accept",
    "tough-dolls-explain",
    "tough-fireants-double",
    "tough-peas-teach",
    "tough-pots-grow",
    "tough-roses-hunt",
    "tricky-bikes-fix",
    "tricky-boxes-juggle",
    "tricky-buses-march",
    "tricky-swans-develop",
    "twelve-lions-remain",
    "twenty-elephants-try",
    "twenty-lamps-rule",
    "twenty-yaks-behave",
    "two-countries-invite",
    "two-crews-talk",
    "two-nails-smash",
    "two-pumas-doubt",
    "two-terms-speak",
    "unlucky-bags-peel",
    "unlucky-emus-bow",
    "unlucky-foxes-itch",
    "unlucky-frogs-tap",
    "unlucky-socks-heal",
    "violet-birds-scream",
    "violet-penguins-nail",
    "violet-roses-look",
    "warm-apricots-design",
    "warm-books-begin",
    "warm-dragons-think",
    "warm-icons-brake",
    "warm-jars-camp",
    "warm-news-wonder",
    "weak-bears-cover",
    "weak-elephants-grin",
    "weak-feet-love",
    "weak-pants-warn",
    "weak-trees-kneel",
    "wet-bats-tickle",
    "wet-carpets-double",
    "wet-seals-breathe",
    "wicked-bears-laugh",
    "wicked-countries-explain",
    "wicked-spoons-confess",
    "wicked-suits-remain",
    "wicked-wasps-retire",
    "wild-cougars-greet",
    "wild-cycles-jog",
    "wild-emus-whisper",
    "wild-hats-sin",
    "wild-phones-smoke",
    "wise-drinks-divide",
    "wise-houses-shop",
    "wise-lions-type",
    "wise-scissors-know",
    "witty-eggs-punch",
    "witty-forks-cheer",
    "witty-jokes-repair",
    "witty-pens-arrive",
    "witty-shirts-dream",
    "yellow-elephants-begin",
    "yellow-frogs-teach",
    "yellow-papayas-help",
    "yellow-tigers-know",
    "yellow-walls-worry",
    "young-experts-attack",
    "young-frogs-enjoy",
    "young-guests-help",
    "young-items-explode"
  ]
}
